gaxkey/TUTORIAL.md
gaxkey/server_main.py
gaxkey/__init__.py
gaxkey/_core.cpython-310-x86_64-linux-gnu.so
gaxkey/__init__.pyi
gaxkey/client_main.py
gaxkey-0.2.25.dist-info/METADATA
gaxkey-0.2.25.dist-info/entry_points.txt
gaxkey-0.2.25.dist-info/WHEEL
gaxkey-0.2.25.dist-info/RECORD
